xpublish/__init__.py
xpublish/accessor.py
xpublish/dependencies.py
xpublish/rest.py
xpublish/plugins/__init__.py
xpublish/plugins/hooks.py
xpublish/plugins/manage.py
xpublish/plugins/included/dataset_info.py
xpublish/plugins/included/module_version.py
xpublish/plugins/included/plugin_info.py
xpublish/plugins/included/zarr.py
xpublish/routers/__init__.py
xpublish/routers/common.py
xpublish/utils/__init__.py
xpublish/utils/api.py
xpublish/utils/cache.py
xpublish/utils/info.py
xpublish/utils/zarr.py
xpublish-0.4.1.dist-info/licenses/LICENSE
xpublish-0.4.1.dist-info/METADATA
xpublish-0.4.1.dist-info/WHEEL
xpublish-0.4.1.dist-info/entry_points.txt
xpublish-0.4.1.dist-info/top_level.txt
xpublish-0.4.1.dist-info/RECORD
