Metadata-Version: 2.4
Name: xpublish
Version: 0.4.1
Summary: Publish Xarray Datasets via a REST API.
Maintainer-email: Joe Hamman <jhamman@ucar.edu>, Alex Kerney <akerney@gmri.org>
License: 
Project-URL: documentation, https://xpublish.readthedocs.io/
Project-URL: repository, https://github.com/xpublish-community/xpublish
Keywords: api,xarray,zarr
Classifier: Development Status :: 4 - Beta
Classifier: Intended Audience :: Science/Research
Classifier: License :: OSI Approved :: MIT License
Classifier: Operating System :: OS Independent
Classifier: Programming Language :: Python
Classifier: Programming Language :: Python :: 3 :: Only
Classifier: Programming Language :: Python :: 3.11
Classifier: Programming Language :: Python :: 3.12
Classifier: Programming Language :: Python :: 3.13
Classifier: Topic :: Scientific/Engineering
Requires-Python: >=3.11
License-File: LICENSE
Requires-Dist: cachey
Requires-Dist: dask
Requires-Dist: fastapi>=0.115.0
Requires-Dist: numcodecs
Requires-Dist: numpy
Requires-Dist: pluggy
Requires-Dist: pydantic>=2.5.0
Requires-Dist: toolz
Requires-Dist: uvicorn
Requires-Dist: xarray>=2025.1.0
Requires-Dist: zarr>=3.0.7
Dynamic: license-file
